file_sorter/__init__.py
file_sorter/find_unique_files.py
file_sorter/find_unique_images.py
file_sorter/images.py
file_sorter/move_duplicates.py
file_sorter/support.py
file_sorter/urls.py
file_sorter-0.0.1.dist-info/LICENSE
file_sorter-0.0.1.dist-info/METADATA
file_sorter-0.0.1.dist-info/WHEEL
file_sorter-0.0.1.dist-info/top_level.txt
file_sorter-0.0.1.dist-info/RECORD
